{
    "python.jediEnabled": false,
    "languageserver": {
        "clangd": {
            "command": "clangd",
            "args": ["--background-index"],
            "rootPatterns": ["compile_flags.txt", "compile_commands.json", ".vim/", ".git/", ".hg/"],
            "filetypes": ["c", "cpp", "objc", "objcpp"]
        },
        "golang": {
            "command": "gopls",
            "rootPatterns": ["go.mod"],
            "filetypes": ["go"]
        },
        "dockerfile": {
            "command": "docker-langserver",
            "filetypes": ["dockerfile"],
            "args": ["--stdio"]
        },
        "bash": {
            "command": "bash-language-server",
            "args": ["start"],
            "filetypes": ["sh"],
            "ignoredRootPaths": ["~"]
        },
        "cmake": {
            "command": "cmake-language-server",
            "filetypes": ["cmake"],
            "rootPatterns": ["build/"],
            "initializationOptions": {
                "buildDirectory": "build"
            }
        }
    }
}
